mod1/__init__.py
mod1/multi.py
mod2/__init__.py
mod2/div.py
cnspary_p2-0.0.1.dist-info/METADATA
cnspary_p2-0.0.1.dist-info/WHEEL
cnspary_p2-0.0.1.dist-info/top_level.txt
cnspary_p2-0.0.1.dist-info/RECORD
