Metadata-Version: 2.1
Name: cnspary-p2
Version: 0.0.1
Summary: MC-PackageTwo
Author: cnspary
Author-email: cnspary@outlook.com
Requires-Python: >=3.0
